sparse_dot_topn/__init__.py
sparse_dot_topn/types.py
sparse_dot_topn/api.py
sparse_dot_topn/unchecked.py
sparse_dot_topn/.dylibs/libomp.dylib
sparse_dot_topn/lib/.gitkeep
sparse_dot_topn/lib/_sparse_dot_topn_core.cpython-310-darwin.so
sparse_dot_topn-1.2.0.dist-info/RECORD
sparse_dot_topn-1.2.0.dist-info/WHEEL
sparse_dot_topn-1.2.0.dist-info/METADATA
sparse_dot_topn-1.2.0.dist-info/licenses/LICENSE
sparse_dot_topn-1.2.0.dist-info/licenses/NOTICE
