Metadata-Version: 2.1
Name: sparse-dot-topn
Version: 1.2.0
Summary: This package boosts a sparse matrix multiplication followed by selecting the top-n multiplication
Author-Email: ING Analytics Wholesale Banking <wbaa@ing.com>
Classifier: License :: OSI Approved :: Apache Software License
Classifier: Programming Language :: Python :: 3
Classifier: Operating System :: OS Independent
Project-URL: Homepage, https://github.com/ing-bank/sparse_dot_topn
Requires-Python: >=3.9
Requires-Dist: numpy>=1.18.0
Requires-Dist: scipy>=1.4.1
Requires-Dist: psutil
Provides-Extra: test
Requires-Dist: pytest>=4.0.2; extra == "test"
